tilapia_freshness/__init__.py
tilapia_freshness/assets/__init__.py
tilapia_freshness/assets/icon.png
tilapia_freshness/config/__init__.py
tilapia_freshness/config/settings.py
tilapia_freshness/enums/__init__.py
tilapia_freshness/enums/constants.py
tilapia_freshness/exceptions/__init__.py
tilapia_freshness/exceptions/analysis_errors.py
tilapia_freshness/exceptions/base.py
tilapia_freshness/exceptions/file_errors.py
tilapia_freshness/exceptions/model_errors.py
tilapia_freshness/gui/__init__.py
tilapia_freshness/gui/main_window.py
tilapia_freshness/models/__init__.py
tilapia_freshness/models/analyzer.py
tilapia_freshness/models/detector.py
tilapia_freshness/models/segmentation.py
tilapia_freshness/utils/__init__.py
tilapia_freshness/utils/cache.py
tilapia_freshness/utils/file_naming.py
tilapia_freshness/utils/logger.py
tilapia_freshness/utils/progress.py
tilapia_freshness/utils/resources.py
tilapia_freshness_evaluator-1.0.0.dist-info/licenses/LICENSE
tilapia_freshness_evaluator-1.0.0.dist-info/METADATA
tilapia_freshness_evaluator-1.0.0.dist-info/WHEEL
tilapia_freshness_evaluator-1.0.0.dist-info/entry_points.txt
tilapia_freshness_evaluator-1.0.0.dist-info/top_level.txt
tilapia_freshness_evaluator-1.0.0.dist-info/RECORD
