Metadata-Version: 2.4
Name: tilapia-freshness-evaluator
Version: 1.0.0
Summary: A computer vision system for evaluating tilapia fish freshness
Author: Dustin Uriel Obispo, King Red Sanchez, Briel Aldous Viola
Author-email: John Elway Cortez <elwaycortez@gmail.com>
Maintainer-email: John Elway Cortez <elwaycortez@gmail.com>
License: MIT
Project-URL: Homepage, https://github.com/Evrouin/tilapia-fish-freshness-evaluation-system
Project-URL: Repository, https://github.com/Evrouin/tilapia-fish-freshness-evaluation-system
Project-URL: Issues, https://github.com/Evrouin/tilapia-fish-freshness-evaluation-system/issues
Keywords: computer-vision,fish-freshness,yolo,opencv,image-processing
Classifier: Development Status :: 4 - Beta
Classifier: Intended Audience :: Science/Research
Classifier: License :: OSI Approved :: MIT License
Classifier: Operating System :: OS Independent
Classifier: Programming Language :: Python :: 3
Classifier: Programming Language :: Python :: 3.11
Classifier: Programming Language :: Python :: 3.12
Classifier: Topic :: Scientific/Engineering :: Image Processing
Classifier: Topic :: Scientific/Engineering :: Artificial Intelligence
Requires-Python: >=3.11
License-File: LICENSE
Requires-Dist: opencv-python==4.12.0.88
Requires-Dist: pillow==12.0.0
Requires-Dist: numpy==2.2.6
Provides-Extra: dev
Requires-Dist: mypy>=1.0.0; extra == "dev"
Requires-Dist: black>=22.0.0; extra == "dev"
Requires-Dist: isort>=5.10.0; extra == "dev"
Requires-Dist: flake8>=4.0.0; extra == "dev"
Requires-Dist: pre-commit>=2.17.0; extra == "dev"
Requires-Dist: pytest>=7.0.0; extra == "dev"
Requires-Dist: pytest-cov>=4.0.0; extra == "dev"
Dynamic: license-file
